Workbook

Sheet Assumptions
A1: Solstice | Assumptions
A2: Solar nameplate (MW) | B2: 200
A3: Capacity factor | B3: 0.25
A4: Annual degradation | B4: 0.005
A5: Storage power (MW) | B5: 50
A6: Storage capacity pmt ($/kW-mo) | B6: 9
A7: Capex ($) | B7: 230000000
A8: PPA price ($/MWh) | B8: 58
A9: PPA term (yrs) | B9: 20
A10: Merchant price ($/MWh) | B10: 42
A11: Escalation | B11: 0.02
A12: Fixed O&M, yr1 ($) | B12: 4000000
A13: Operating life (yrs) | B13: 30
... A19: Grid emissions factor (t/MWh) | B19: 0.4
A21: Debt drawn ($) | B21: =B7*B14
A22: Equity ($) | B22: =B7-B21
A23: Level debt pmt ($) | B23: =B21*B15/(1-(1+B15)^-B16)
A24: Depreciation/yr ($) | B24: =B7/B13

Sheet Model
A1: Year | B1: Generation (MWh) | C1: Energy price ($/MWh) | D1: Energy revenue ($) | E1: Storage revenue ($) | F1: Revenue ($) | G1: Opex ($) | H1: EBITDA ($) | I1: Depreciation ($) | J1: Interest ($) | K1: Principal ($) | L1: Debt balance ($) | M1: Tax-levered ($) | N1: Equity cash flow ($) | O1: Unlevered FCF ($) | P1: DSCR
A2: 0 | D2: 0 | E2: 0 | F2: 0 | G2: 0 | H2: 0 | I2: 0 | J2: 0 | K2: 0 | L2: =Assumptions!$B$21 | M2: 0 | N2: =-Assumptions!$B$22 | O2: =-Assumptions!$B$7
A3: 1 | B3: =Assumptions!$B$2*8760*Assumptions!$B$3*(1-Assumptions!$B$4)^(A3-1) | C3: =IF(A3<=Assumptions!$B$9,Assumptions!$B$8*(1+Assumptions!$B$11)^(A3-1),Assumptions!$B$10*(1+Assumptions!$B$11)^(A3-Assumptions!$B$9-1)) | D3: =B3*C3 | E3: =Assumptions!$B$5*1000*Assumptions!$B$6*12*(1+Assumptions!$B$11)^(A3-1) | F3: =D3+E3 | G3: =Assumptions!$B$12*(1+Assumptions!$B$11)^(A3-1) | H3: =F3-G3 | I3: =Assumptions!$B$24 | J3: =IF(A3<=Assumptions!$B$16,L2*Assumptions!$B$15,0) | K3: =IF(A3<=Assumptions!$B$16,Assumptions!$B$23-J3,0) | L3: =IF(A3<=Assumptions!$B$16,L2-K3,0) | M3: =MAX(0,H3-I3-J3)*Assumptions!$B$17 | N3: =H3-J3-K3-M3 | O3: =H3-MAX(0,H3-I3)*Assumptions!$B$17 | P3: =IF(A3<=Assumptions!$B$16,H3/(J3+K3),"")
A4: 2 | B4: =Assumptions!$B$2*8760*Assumptions!$B$3*(1-Assumptions!$B$4)^(A4-1) | C4: =IF(A4<=Assumptions!$B$9,Assumptions!$B$8*(1+Assumptions!$B$11)^(A4-1),Assumptions!$B$10*(1+Assumptions!$B$11)^(A4-Assumptions!$B$9-1)) | D4: =B4*C4 | E4: =Assumptions!$B$5*1000*Assumptions!$B$6*12*(1+Assumptions!$B$11)^(A4-1) | F4: =D4+E4 | G4: =Assumptions!$B$12*(1+Assumptions!$B$11)^(A4-1) | H4: =F4-G4 | I4: =Assumptions!$B$24 | J4: =IF(A4<=Assumptions!$B$16,L3*Assumptions!$B$15,0) | K4: =IF(A4<=Assumptions!$B$16,Assumptions!$B$23-J4,0) | L4: =IF(A4<=Assumptions!$B$16,L3-K4,0) | M4: =MAX(0,H4-I4-J4)*Assumptions!$B$17 | N4: =H4-J4-K4-M4 | O4: =H4-MAX(0,H4-I4)*Assumptions!$B$17 | P4: =IF(A4<=Assumptions!$B$16,H4/(J4+K4),"")
A5: 3 | B5: =Assumptions!$B$2*8760*Assumptions!$B$3*(1-Assumptions!$B$4)^(A5-1) | C5: =IF(A5<=Assumptions!$B$9,Assumptions!$B$8*(1+Assumptions!$B$11)^(A5-1),Assumptions!$B$10*(1+Assumptions!$B$11)^(A5-Assumptions!$B$9-1)) | D5: =B5*C5 | E5: =Assumptions!$B$5*1000*Assumptions!$B$6*12*(1+Assumptions!$B$11)^(A5-1) | F5: =D5+E5 | G5: =Assumptions!$B$12*(1+Assumptions!$B$11)^(A5-1) | H5: =F5-G5 | I5: =Assumptions!$B$24 | J5: =IF(A5<=Assumptions!$B$16,L4*Assumptions!$B$15,0) | K5: =IF(A5<=Assumptions!$B$16,Assumptions!$B$23-J5,0) | L5: =IF(A5<=Assumptions!$B$16,L4-K5,0) | M5: =MAX(0,H5-I5-J5)*Assumptions!$B$17 | N5: =H5-J5-K5-M5 | O5: =H5-MAX(0,H5-I5)*Assumptions!$B$17 | P5: =IF(A5<=Assumptions!$B$16,H5/(J5+K5),"")
A6: 4 | B6: =Assumptions!$B$2*8760*Assumptions!$B$3*(1-Assumptions!$B$4)^(A6-1) | C6: =IF(A6<=Assumptions!$B$9,Assumptions!$B$8*(1+Assumptions!$B$11)^(A6-1),Assumptions!$B$10*(1+Assumptions!$B$11)^(A6-Assumptions!$B$9-1)) | D6: =B6*C6 | E6: =Assumptions!$B$5*1000*Assumptions!$B$6*12*(1+Assumptions!$B$11)^(A6-1) | F6: =D6+E6 | G6: =Assumptions!$B$12*(1+Assumptions!$B$11)^(A6-1) | H6: =F6-G6 | I6: =Assumptions!$B$24 | J6: =IF(A6<=Assumptions!$B$16,L5*Assumptions!$B$15,0) | K6: =IF(A6<=Assumptions!$B$16,Assumptions!$B$23-J6,0) | L6: =IF(A6<=Assumptions!$B$16,L5-K6,0) | M6: =MAX(0,H6-I6-J6)*Assumptions!$B$17 | N6: =H6-J6-K6-M6 | O6: =H6-MAX(0,H6-I6)*Assumptions!$B$17 | P6: =IF(A6<=Assumptions!$B$16,H6/(J6+K6),"")
A7: 5 | B7: =Assumptions!$B$2*8760*Assumptions!$B$3*(1-Assumptions!$B$4)^(A7-1) | C7: =IF(A7<=Assumptions!$B$9,Assumptions!$B$8*(1+Assumptions!$B$11)^(A7-1),Assumptions!$B$10*(1+Assumptions!$B$11)^(A7-Assumptions!$B$9-1)) | D7: =B7*C7 | E7: =Assumptions!$B$5*1000*Assumptions!$B$6*12*(1+Assumptions!$B$11)^(A7-1) | F7: =D7+E7 | G7: =Assumptions!$B$12*(1+Assumptions!$B$11)^(A7-1) | H7: =F7-G7 | I7: =Assumptions!$B$24 | J7: =IF(A7<=Assumptions!$B$16,L6*Assumptions!$B$15,0) | K7: =IF(A7<=Assumptions!$B$16,Assumptions!$B$23-J7,0) | L7: =IF(A7<=Assumptions!$B$16,L6-K7,0) | M7: =MAX(0,H7-I7-J7)*Assumptions!$B$17 | N7: =H7-J7-K7-M7 | O7: =H7-MAX(0,H7-I7)*Assumptions!$B$17 | P7: =IF(A7<=Assumptions!$B$16,H7/(J7+K7),"")
A8: 6 | B8: =Assumptions!$B$2*8760*Assumptions!$B$3*(1-Assumptions!$B$4)^(A8-1) | C8: =IF(A8<=Assumptions!$B$9,Assumptions!$B$8*(1+Assumptions!$B$11)^(A8-1),Assumptions!$B$10*(1+Assumptions!$B$11)^(A8-Assumptions!$B$9-1)) | D8: =B8*C8 | E8: =Assumptions!$B$5*1000*Assumptions!$B$6*12*(1+Assumptions!$B$11)^(A8-1) | F8: =D8+E8 | G8: =Assumptions!$B$12*(1+Assumptions!$B$11)^(A8-1) | H8: =F8-G8 | I8: =Assumptions!$B$24 | J8: =IF(A8<=Assumptions!$B$16,L7*Assumptions!$B$15,0) | K8: =IF(A8<=Assumptions!$B$16,Assumptions!$B$23-J8,0) | L8: =IF(A8<=Assumptions!$B$16,L7-K8,0) | M8: =MAX(0,H8-I8-J8)*Assumptions!$B$17 | N8: =H8-J8-K8-M8 | O8: =H8-MAX(0,H8-I8)*Assumptions!$B$17 | P8: =IF(A8<=Assumptions!$B$16,H8/(J8+K8),"")
A9: 7 | B9: =Assumptions!$B$2*8760*Assumptions!$B$3*(1-Assumptions!$B$4)^(A9-1) | C9: =IF(A9<=Assumptions!$B$9,Assumptions!$B$8*(1+Assumptions!$B$11)^(A9-1),Assumptions!$B$10*(1+Assumptions!$B$11)^(A9-Assumptions!$B$9-1)) | D9: =B9*C9 | E9: =Assumptions!$B$5*1000*Assumptions!$B$6*12*(1+Assumptions!$B$11)^(A9-1) | F9: =D9+E9 | G9: =Assumptions!$B$12*(1+Assumptions!$B$11)^(A9-1) | H9: =F9-G9 | I9: =Assumptions!$B$24 | J9: =IF(A9<=Assumptions!$B$16,L8*Assumptions!$B$15,0) | K9: =IF(A9<=Assumptions!$B$16,Assumptions!$B$23-J9,0) | L9: =IF(A9<=Assumptions!$B$16,L8-K9,0) | M9: =MAX(0,H9-I9-J9)*Assumptions!$B$17 | N9: =H9-J9-K9-M9 | O9: =H9-MAX(0,H9-I9)*Assumptions!$B$17 | P9: =IF(A9<=Assumptions!$B$16,H9/(J9+K9),"")
A10: 8 | B10: =Assumptions!$B$2*8760*Assumptions!$B$3*(1-Assumptions!$B$4)^(A10-1) | C10: =IF(A10<=Assumptions!$B$9,Assumptions!$B$8*(1+Assumptions!$B$11)^(A10-1),Assumptions!$B$10*(1+Assumptions!$B$11)^(A10-Assumptions!$B$9-1)) | D10: =B10*C10 | E10: =Assumptions!$B$5*1000*Assumptions!$B$6*12*(1+Assumptions!$B$11)^(A10-1) | F10: =D10+E10 | G10: =Assumptions!$B$12*(1+Assumptions!$B$11)^(A10-1) | H10: =F10-G10 | I10: =Assumptions!$B$24 | J10: =IF(A10<=Assumptions!$B$16,L9*Assumptions!$B$15,0) | K10: =IF(A10<=Assumptions!$B$16,Assumptions!$B$23-J10,0) | L10: =IF(A10<=Assumptions!$B$16,L9-K10,0) | M10: =MAX(0,H10-I10-J10)*Assumptions!$B$17 | N10: =H10-J10-K10-M10 | O10: =H10-MAX(0,H10-I10)*Assumptions!$B$17 | P10: =IF(A10<=Assumptions!$B$16,H10/(J10+K10),"")
A11: 9 | B11: =Assumptions!$B$2*8760*Assumptions!$B$3*(1-Assumptions!$B$4)^(A11-1) | C11: =IF(A11<=Assumptions!$B$9,Assumptions!$B$8*(1+Assumptions!$B$11)^(A11-1),Assumptions!$B$10*(1+Assumptions!$B$11)^(A11-Assumptions!$B$9-1)) | D11: =B11*C11 | E11: =Assumptions!$B$5*1000*Assumptions!$B$6*12*(1+Assumptions!$B$11)^(A11-1) | F11: =D11+E11 | G11: =Assumptions!$B$12*(1+Assumptions!$B$11)^(A11-1) | H11: =F11-G11 | I11: =Assumptions!$B$24 | J11: =IF(A11<=Assumptions!$B$16,L10*Assumptions!$B$15,0) | K11: =IF(A11<=Assumptions!$B$16,Assumptions!$B$23-J11,0) | L11: =IF(A11<=Assumptions!$B$16,L10-K11,0) | M11: =MAX(0,H11-I11-J11)*Assumptions!$B$17 | N11: =H11-J11-K11-M11 | O11: =H11-MAX(0,H11-I11)*Assumptions!$B$17 | P11: =IF(A11<=Assumptions!$B$16,H11/(J11+K11),"")
A12: 10 | B12: =Assumptions!$B$2*8760*Assumptions!$B$3*(1-Assumptions!$B$4)^(A12-1) | C12: =IF(A12<=Assumptions!$B$9,Assumptions!$B$8*(1+Assumptions!$B$11)^(A12-1),Assumptions!$B$10*(1+Assumptions!$B$11)^(A12-Assumptions!$B$9-1)) | D12: =B12*C12 | E12: =Assumptions!$B$5*1000*Assumptions!$B$6*12*(1+Assumptions!$B$11)^(A12-1) | F12: =D12+E12 | G12: =Assumptions!$B$12*(1+Assumptions!$B$11)^(A12-1) | H12: =F12-G12 | I12: =Assumptions!$B$24 | J12: =IF(A12<=Assumptions!$B$16,L11*Assumptions!$B$15,0) | K12: =IF(A12<=Assumptions!$B$16,Assumptions!$B$23-J12,0) | L12: =IF(A12<=Assumptions!$B$16,L11-K12,0) | M12: =MAX(0,H12-I12-J12)*Assumptions!$B$17 | N12: =H12-J12-K12-M12 | O12: =H12-MAX(0,H12-I12)*Assumptions!$B$17 | P12: =IF(A12<=Assumptions!$B$16,H12/(J12+K12),"")
A13: 11 | B13: =Assumptions!$B$2*8760*Assumptions!$B$3*(1-Assumptions!$B$4)^(A13-1) | C13: =IF(A13<=Assumptions!$B$9,Assumptions!$B$8*(1+Assumptions!$B$11)^(A13-1),Assumptions!$B$10*(1+Assumptions!$B$11)^(A13-Assumptions!$B$9-1)) | D13: =B13*C13 | E13: =Assumptions!$B$5*1000*Assumptions!$B$6*12*(1+Assumptions!$B$11)^(A13-1) | F13: =D13+E13 | G13: =Assumptions!$B$12*(1+Assumptions!$B$11)^(A13-1) | H13: =F13-G13 | I13: =Assumptions!$B$24 | J13: =IF(A13<=Assumptions!$B$16,L12*Assumptions!$B$15,0) | K13: =IF(A13<=Assumptions!$B$16,Assumptions!$B$23-J13,0) | L13: =IF(A13<=Assumptions!$B$16,L12-K13,0) | M13: =MAX(0,H13-I13-J13)*Assumptions!$B$17 | N13: =H13-J13-K13-M13 | O13: =H13-MAX(0,H13-I13)*Assumptions!$B$17 | P13: =IF(A13<=Assumptions!$B$16,H13/(J13+K13),"")
A14: 12 | B14: =Assumptions!$B$2*8760*Assumptions!$B$3*(1-Assumptions!$B$4)^(A14-1) | C14: =IF(A14<=Assumptions!$B$9,Assumptions!$B$8*(1+Assumptions!$B$11)^(A14-1),Assumptions!$B$10*(1+Assumptions!$B$11)^(A14-Assumptions!$B$9-1)) | D14: =B14*C14 | E14: =Assumptions!$B$5*1000*Assumptions!$B$6*12*(1+Assumptions!$B$11)^(A14-1) | F14: =D14+E14 | G14: =Assumptions!$B$12*(1+Assumptions!$B$11)^(A14-1) | H14: =F14-G14 | I14: =Assumptions!$B$24 | J14: =IF(A14<=Assumptions!$B$16,L13*Assumptions!$B$15,0) | K14: =IF(A14<=Assumptions!$B$16,Assumptions!$B$23-J14,0) | L14: =IF(A14<=Assumptions!$B$16,L13-K14,0) | M14: =MAX(0,H14-I14-J14)*Assumptions!$B$17 | N14: =H14-J14-K14-M14 | O14: =H14-MAX(0,H14-I14)*Assumptions!$B$17 | P14: =IF(A14<=Assumptions!$B$16,H14/(J14+K14),"")
... A32: 30 | B32: =Assumptions!$B$2*8760*Assumptions!$B$3*(1-Assumptions!$B$4)^(A32-1) | C32: =IF(A32<=Assumptions!$B$9,Assumptions!$B$8*(1+Assumptions!$B$11)^(A32-1),Assumptions!$B$10*(1+Assumptions!$B$11)^(A32-Assumptions!$B$9-1)) | D32: =B32*C32 | E32: =Assumptions!$B$5*1000*Assumptions!$B$6*12*(1+Assumptions!$B$11)^(A32-1) | F32: =D32+E32 | G32: =Assumptions!$B$12*(1+Assumptions!$B$11)^(A32-1) | H32: =F32-G32 | I32: =Assumptions!$B$24 | J32: =IF(A32<=Assumptions!$B$16,L31*Assumptions!$B$15,0) | K32: =IF(A32<=Assumptions!$B$16,Assumptions!$B$23-J32,0) | L32: =IF(A32<=Assumptions!$B$16,L31-K32,0) | M32: =MAX(0,H32-I32-J32)*Assumptions!$B$17 | N32: =H32-J32-K32-M32 | O32: =H32-MAX(0,H32-I32)*Assumptions!$B$17 | P32: =IF(A32<=Assumptions!$B$16,H32/(J32+K32),"")
A34: RETURNS
A35: Unlevered project IRR | B35: =IRR(O2:O32)
A36: Unlevered NPV @ disc rate ($) | B36: =O2+NPV(Assumptions!B18,O3:O32)
A37: Levered equity IRR | B37: =IRR(N2:N32)
A38: Equity MOIC | B38: =SUM(N3:N32)/-N2
A39: Minimum DSCR | B39: =MIN(P3:P32)

Sheet Sensitivity
A1: Levered equity IRR sensitivity
A2: Rows: capex change | Columns: PPA price change ($/MWh)
A4: capex \ PPA | B4: -6 | C4: -3 | D4: +0 | E4: +3 | F4: +6
A5: -10% | B5: 0.15075762 | C5: 0.16360407 | D5: 0.1766178 | E5: 0.18976476 | F5: 0.20301615
A6: -5% | B6: 0.1379538 | C6: 0.15001448 | D6: 0.16225029 | E6: 0.17462844 | F6: 0.1871204
A7: +0% | B7: 0.12645164 | C7: 0.13780414 | D7: 0.14933706 | E7: 0.1610194 | F7: 0.17282341
A8: +5% | B8: 0.11605888 | C8: 0.12677112 | D8: 0.13766676 | E8: 0.14871692 | F8: 0.15989511
A9: +10% | B9: 0.10661845 | C9: 0.11675015 | D9: 0.12706626 | E9: 0.13754021 | F9: 0.14814701
